finfun/Interest.py
finfun/__init__.py
finfun-0.0.3.dist-info/LICENSE
finfun-0.0.3.dist-info/METADATA
finfun-0.0.3.dist-info/WHEEL
finfun-0.0.3.dist-info/top_level.txt
finfun-0.0.3.dist-info/RECORD
